analysta/__about__.py
analysta/__init__.py
analysta/delta.py
analysta/diff.py
analysta-0.0.4.dist-info/METADATA
analysta-0.0.4.dist-info/WHEEL
analysta-0.0.4.dist-info/licenses/LICENSE.txt
analysta-0.0.4.dist-info/RECORD
